skb/__init__.py
skb/skb.py
skb-1.2.9.dist-info/entry_points.txt
skb-1.2.9.dist-info/LICENSE
skb-1.2.9.dist-info/WHEEL
skb-1.2.9.dist-info/METADATA
skb-1.2.9.dist-info/RECORD
